Metadata-Version: 2.1
Name: kswutils
Version: 0.3.2
Summary: Justin utils at work
Author-email: shuwa108@gmail.com
